crisprbact/__init__.py
crisprbact/cli.py
crisprbact/off_target.py
crisprbact/predict.py
crisprbact/reg_coef.pkl
crisprbact/utils.py
crisprbact-0.3.11.dist-info/entry_points.txt
crisprbact-0.3.11.dist-info/LICENSE
crisprbact-0.3.11.dist-info/WHEEL
crisprbact-0.3.11.dist-info/METADATA
crisprbact-0.3.11.dist-info/RECORD
