Metadata-Version: 2.1
Name: crisprbact
Version: 0.3.11
Summary: Tools to design and analyse CRISPRi experiments
Home-page: https://gitlab.pasteur.fr/dbikard/crisprbact
License: GPL-3.0
Keywords: CRISPR,genomics,bacteria,CRISPRi,screen
Author: David Bikard
Author-email: david.bikard@pasteur.fr
Requires-Python: >=3.7,<4.0
Classifier: Environment :: Console
Classifier: Intended Audience :: Science/Research
Classifier: License :: OSI Approved :: GNU General Public License v3 (GPLv3)
Classifier: Natural Language :: English
Classifier: Operating System :: POSIX :: Linux
Classifier: Programming Language :: Python :: 3
Classifier: Programming Language :: Python :: 3.7
Classifier: Programming Language :: Python :: 3.8
Classifier: Topic :: Scientific/Engineering :: Bio-Informatics
Requires-Dist: biopython (>=1.75,<2.0)
Requires-Dist: click (>=7.0,<8.0)
Requires-Dist: numpy (>=1.17,<2.0)
Requires-Dist: pandas (>=1.0.0,<2.0.0)
Requires-Dist: rope (>=0.16.0,<0.17.0)
